zampy/__init__.py
zampy/cli.py
zampy/recipe.py
zampy/conventions/ALMA.json
zampy/datasets/__init__.py
zampy/datasets/cams.py
zampy/datasets/catalog.py
zampy/datasets/cds_utils.py
zampy/datasets/converter.py
zampy/datasets/dataset_protocol.py
zampy/datasets/ecmwf_dataset.py
zampy/datasets/era5.py
zampy/datasets/eth_canopy_height.py
zampy/datasets/fapar_lai.py
zampy/datasets/land_cover.py
zampy/datasets/prism_dem.py
zampy/datasets/utils.py
zampy/datasets/validation.py
zampy/datasets/assets/dem_filenames_glo30.txt.gz
zampy/datasets/assets/dem_filenames_glo90.txt.gz
zampy/datasets/assets/h_canopy_filenames_compressed.txt.gz
zampy/reference/README.md
zampy/reference/variables.py
zampy-0.2.0.dist-info/METADATA
zampy-0.2.0.dist-info/WHEEL
zampy-0.2.0.dist-info/entry_points.txt
zampy-0.2.0.dist-info/licenses/LICENSE
zampy-0.2.0.dist-info/RECORD
