Metadata-Version: 2.3
Name: zampy
Version: 0.2.0
Summary: python package for getting Land Surface Model input data.
Author: Bart Schilperoort, Yang Liu, Fakhereh Alidoost
Author-email: b.schilperoort@esciencecenter.nl
Maintainer-email: Bart Schilperoort <b.schilperoort@esciencecenter.nl>, Yang Liu <y.liu@esciencecenter.nl>, Fakhereh Alidoost <f.alidoost@esciencecenter.nl>
License-Expression: Apache-2.0
License-File: LICENSE
Keywords: data
Classifier: Development Status :: 2 - Pre-Alpha
Classifier: Intended Audience :: Developers
Classifier: License :: OSI Approved :: Apache Software License
Classifier: Natural Language :: English
Classifier: Operating System :: OS Independent
Classifier: Programming Language :: Python
Classifier: Programming Language :: Python :: 3 :: Only
Classifier: Programming Language :: Python :: 3.10
Classifier: Programming Language :: Python :: 3.11
Requires-Python: <3.13,>=3.10
Requires-Dist: cdsapi
Requires-Dist: cf-xarray
Requires-Dist: dask[diagnostics]
Requires-Dist: distributed
Requires-Dist: matplotlib
Requires-Dist: netcdf4
Requires-Dist: numpy
Requires-Dist: pandas
Requires-Dist: pint
Requires-Dist: pint-xarray
Requires-Dist: pyyaml
Requires-Dist: requests
Requires-Dist: rioxarray
Requires-Dist: scipy
Requires-Dist: tqdm
Requires-Dist: xarray
Requires-Dist: xarray-regrid
Provides-Extra: dev
Requires-Dist: bump2version; extra == 'dev'
Requires-Dist: hatch; extra == 'dev'
Requires-Dist: mypy; extra == 'dev'
Requires-Dist: pre-commit; extra == 'dev'
Requires-Dist: pytest; extra == 'dev'
Requires-Dist: pytest-cov; extra == 'dev'
Requires-Dist: pytest-mock; extra == 'dev'
Requires-Dist: ruff>0.1.2; extra == 'dev'
Requires-Dist: types-pyyaml; extra == 'dev'
Requires-Dist: types-requests; extra == 'dev'
Requires-Dist: types-urllib3; extra == 'dev'
Provides-Extra: docs
Requires-Dist: mkdocs; extra == 'docs'
Requires-Dist: mkdocs-gen-files; extra == 'docs'
Requires-Dist: mkdocs-jupyter; extra == 'docs'
Requires-Dist: mkdocs-material; extra == 'docs'
Requires-Dist: mkdocstrings[python]; extra == 'docs'
